victoria/__init__.py
victoria/config.py
victoria/plugin.py
victoria/util.py
victoria/victoria_example.yaml
victoria/encryption/__init__.py
victoria/encryption/azure_provider.py
victoria/encryption/provider.py
victoria/encryption/schemas.py
victoria/script/__init__.py
victoria/script/victoria.py
victoria/storage/__init__.py
victoria/storage/azure_provider.py
victoria/storage/local_provider.py
victoria/storage/provider.py
victoria_config/__init__.py
victoria_config/functionality.py
victoria_config/schema.py
victoria_encrypt/__init__.py
victoria_store/__init__.py
victoria-1.0.5.dist-info/LICENSE
victoria-1.0.5.dist-info/METADATA
victoria-1.0.5.dist-info/WHEEL
victoria-1.0.5.dist-info/entry_points.txt
victoria-1.0.5.dist-info/top_level.txt
victoria-1.0.5.dist-info/RECORD
