Metadata-Version: 2.1
Name: victoria
Version: 1.0.5
Summary: Automation toolbelt -- a single command with multiple pluggable subcommands for automating any number of 'toil' tasks that inhibit productivity.
Home-page: https://github.com/glasswall-sre/victoria
Author: Glasswall SRE
Author-email: sre@glasswallsolutions.com
License: UNKNOWN
Keywords: cli automation sre plugin
Platform: UNKNOWN
Classifier: Development Status :: 4 - Beta
Classifier: Environment :: Console
Classifier: Intended Audience :: Developers
Classifier: Intended Audience :: System Administrators
Classifier: License :: OSI Approved :: MIT License
Classifier: Operating System :: OS Independent
Classifier: Programming Language :: Python :: 3.6
Classifier: Programming Language :: Python :: 3.7
Classifier: Programming Language :: Python :: 3.8
Classifier: Topic :: Terminals
Classifier: Topic :: Utilities
Requires-Python: >=3.6
Requires-Dist: appdirs (>=1.4.3)
Requires-Dist: click (>=7.0)
Requires-Dist: marshmallow (==3.11.1)
Requires-Dist: pyyaml (>=5.1.2)
Requires-Dist: azure-storage-blob (>=12.3.0)
Requires-Dist: cryptography (==3.3.2)
Requires-Dist: azure-keyvault (>=4.0.0)
Requires-Dist: azure-identity (>=1.3.0)
Requires-Dist: dpath (>=2.0.1)
Requires-Dist: azure-cli-core (>=2.18.0)
Requires-Dist: packaging (>=20.9)
